otc/__init__.py
otc/otc.py
otc-4.0.0.dist-info/LICENSE
otc-4.0.0.dist-info/METADATA
otc-4.0.0.dist-info/WHEEL
otc-4.0.0.dist-info/top_level.txt
otc-4.0.0.dist-info/RECORD
